<?xml version="1.0" ?>
<root>
    <agent start_id="n835" goal_id="n9668"/>
    <agent start_id="n4769" goal_id="n5684"/>
    <agent start_id="n5249" goal_id="n1823"/>
    <agent start_id="n1280" goal_id="n1910"/>
    <agent start_id="n3344" goal_id="n4197"/>
    <agent start_id="n4740" goal_id="n1183"/>
    <agent start_id="n3336" goal_id="n2714"/>
    <agent start_id="n4142" goal_id="n885"/>
    <agent start_id="n4748" goal_id="n2089"/>
    <agent start_id="n651" goal_id="n7745"/>
    <agent start_id="n2903" goal_id="n6833"/>
    <agent start_id="n2128" goal_id="n5440"/>
    <agent start_id="n5264" goal_id="n426"/>
    <agent start_id="n1023" goal_id="n1017"/>
    <agent start_id="n6344" goal_id="n2873"/>
    <agent start_id="n8201" goal_id="n3053"/>
    <agent start_id="n2717" goal_id="n49"/>
    <agent start_id="n7025" goal_id="n9497"/>
    <agent start_id="n8732" goal_id="n8577"/>
    <agent start_id="n1459" goal_id="n1937"/>
    <agent start_id="n8688" goal_id="n1463"/>
    <agent start_id="n4465" goal_id="n6566"/>
    <agent start_id="n6168" goal_id="n1774"/>
    <agent start_id="n3048" goal_id="n9044"/>
    <agent start_id="n222" goal_id="n3833"/>
    <agent start_id="n6348" goal_id="n4937"/>
    <agent start_id="n8677" goal_id="n6853"/>
    <agent start_id="n3194" goal_id="n2719"/>
    <agent start_id="n1184" goal_id="n3781"/>
    <agent start_id="n7272" goal_id="n3809"/>
    <agent start_id="n1778" goal_id="n6836"/>
    <agent start_id="n7269" goal_id="n5678"/>
    <agent start_id="n1286" goal_id="n515"/>
    <agent start_id="n203" goal_id="n6032"/>
    <agent start_id="n8431" goal_id="n6557"/>
    <agent start_id="n5616" goal_id="n1300"/>
    <agent start_id="n3668" goal_id="n4469"/>
    <agent start_id="n4210" goal_id="n4756"/>
    <agent start_id="n9217" goal_id="n1613"/>
    <agent start_id="n1114" goal_id="n2702"/>
    <agent start_id="n1606" goal_id="n5369"/>
    <agent start_id="n4271" goal_id="n9473"/>
    <agent start_id="n1599" goal_id="n823"/>
    <agent start_id="n2588" goal_id="n3728"/>
    <agent start_id="n809" goal_id="n8536"/>
    <agent start_id="n1773" goal_id="n8684"/>
    <agent start_id="n7733" goal_id="n8996"/>
    <agent start_id="n1763" goal_id="n1833"/>
    <agent start_id="n3489" goal_id="n954"/>
    <agent start_id="n5714" goal_id="n6825"/>
</root>
